odoo/addons/mrp_bom_line_sequence/README.rst
odoo/addons/mrp_bom_line_sequence/__init__.py
odoo/addons/mrp_bom_line_sequence/__manifest__.py
odoo/addons/mrp_bom_line_sequence/i18n/hr.po
odoo/addons/mrp_bom_line_sequence/i18n/it.po
odoo/addons/mrp_bom_line_sequence/i18n/mrp_bom_line_sequence.pot
odoo/addons/mrp_bom_line_sequence/models/__init__.py
odoo/addons/mrp_bom_line_sequence/models/mrp.py
odoo/addons/mrp_bom_line_sequence/readme/CONTRIBUTORS.rst
odoo/addons/mrp_bom_line_sequence/readme/DESCRIPTION.rst
odoo/addons/mrp_bom_line_sequence/readme/USAGE.rst
odoo/addons/mrp_bom_line_sequence/static/description/icon.png
odoo/addons/mrp_bom_line_sequence/static/description/index.html
odoo/addons/mrp_bom_line_sequence/views/stock_view.xml
odoo_addon_mrp_bom_line_sequence-15.0.1.0.0.6.dist-info/METADATA
odoo_addon_mrp_bom_line_sequence-15.0.1.0.0.6.dist-info/WHEEL
odoo_addon_mrp_bom_line_sequence-15.0.1.0.0.6.dist-info/top_level.txt
odoo_addon_mrp_bom_line_sequence-15.0.1.0.0.6.dist-info/RECORD
